<channels>
<channel>
<name>CANAIS SERVIDOR PSRV 1</name>
<thumbnail></thumbnail>
<externallink>https://github.com/neitzke11/NEITZKE/raw/master/PSRV%201.xml</externallink>
<fanart></fanart>
<info></info>
</channel>
</channels>

<channels>
<channel>
<name>CANAIS SERVIDOR PDSRV 2</name>
<thumbnail></thumbnail>
<externallink>https://github.com/neitzke11/NEITZKE/raw/master/PDSRV%202.xml</externallink>
<fanart></fanart>
<info></info>
</channel>
</channels>

<channel>
<name>CANAIS SERVIDOR PDSRV 1 </name>
<thumbnail></thumbnail>
<externallink>https://github.com/neitzke11/NEITZKE/raw/master/PDSRV%201.xml</externallink>
<fanart></fanart>
<info></info>
</channel>
</channels>

<channels>
<channel>
<name>CANAIS SERVIDOR PDSRV 2</name>
<thumbnail></thumbnail>
<externallink>https://github.com/neitzke11/NEITZKE/raw/master/PDSRV%202.xml</externallink>
<fanart></fanart>
<info></info>
</channel>
</channels>

<channels>
<channel>
<name>CANAIS SERVIDOR PDSRV 3</name>
<thumbnail></thumbnail>
<externallink>https://github.com/neitzke11/NEITZKE/raw/master/PDSRV%203.xml</externallink>
<fanart></fanart>
<info></info>
</channel>
</channels>

<channels>
<channel>
<name>CANAIS SERVIDOR FACTORYIPTV 1</name>
<thumbnail></thumbnail>
<externallink>https://github.com/neitzke11/NEITZKE/raw/master/FACTORY%201.xml</externallink>
<fanart></fanart>
<info></info>
</channel>
</channels>

<channels>
<channel>
<name>CANAIS SERVIDOR FACTORYIPTV 2</name>
<thumbnail></thumbnail>
<externallink>https://github.com/neitzke11/NEITZKE/raw/master/FACTORY%202.xml</externallink>
<fanart></fanart>
<info></info>
</channel>
</channels>

<channels>
<channel>
<name>CANAIS SERVIDOR FACTORYIPTV 3</name>
<thumbnail></thumbnail>
<externallink>https://github.com/neitzke11/NEITZKE/raw/master/FACTORY%203.xml</externallink>
<fanart></fanart>
<info></info>
</channel>
</channels>

<channels>
<channel>
<name>CANAIS SERVIDOR FACTORYIPTV 4</name>
<thumbnail></thumbnail>
<externallink>https://github.com/neitzke11/NEITZKE/raw/master/FACTORY%204.xml</externallink>
<fanart></fanart>
<info></info>
</channel>
</channels>